sshman/Colors.py
sshman/Domain.py
sshman/Dumper.py
sshman/Errors.py
sshman/Runner.py
sshman/SSH.py
sshman/__init__.py
sshman/__main__.py
sshman/sshman_cmd.py
sshman-0.4.3.dist-info/LICENSE
sshman-0.4.3.dist-info/METADATA
sshman-0.4.3.dist-info/WHEEL
sshman-0.4.3.dist-info/entry_points.txt
sshman-0.4.3.dist-info/top_level.txt
sshman-0.4.3.dist-info/RECORD
