Metadata-Version: 2.1
Name: sshman
Version: 0.4.3
Summary: A simple, pure-python, SSH Connection manager.
Home-page: https://github.com/marcocspc/sshman
Author: Marco Antonio
Author-email: marcocspc@hotmail.com
License: gpl-3.0
Download-URL: https://github.com/marcocspc/sshman/archive/refs/tags/0.4.tar.gz
Keywords: ssh,connection,manager
Platform: UNKNOWN
Classifier: Development Status :: 4 - Beta
Classifier: Intended Audience :: Developers
Classifier: Topic :: Software Development :: Build Tools
Classifier: License :: OSI Approved :: GNU General Public License v3 (GPLv3)
Classifier: Programming Language :: Python :: 3
Classifier: Programming Language :: Python :: 3.4
Classifier: Programming Language :: Python :: 3.5
Classifier: Programming Language :: Python :: 3.6
License-File: LICENSE
